personal_streamlit/ai_automation/prompts.py
personal_streamlit/article_translation/article_translation_utils.py
personal_streamlit/data.py
personal_streamlit/energy_tracker/energy_tracker_table.py
personal_streamlit/energy_tracker/notebooks/inspect_energy_tracker.ipynb
personal_streamlit/knowledge_graph/knowledge_graph_table.py
personal_streamlit/learning_assistant/exercise_generator.py
personal_streamlit/pages/admin_page.py
personal_streamlit/pages/ai_automation_page.py
personal_streamlit/pages/all_papers_page.py
personal_streamlit/pages/article_url_translation_page.py
personal_streamlit/pages/content_translation_page.py
personal_streamlit/pages/energy_tracker.py
personal_streamlit/pages/image_evaluator.py
personal_streamlit/pages/interests_page.py
personal_streamlit/pages/learning_assistant_page.py
personal_streamlit/pages/paper_details_page.py
personal_streamlit/pages/papers_with_insights_generated_page.py
personal_streamlit/pages/profile_page.py
personal_streamlit/pages/read_backlog_page.py
personal_streamlit/pages/recommendations_page.py
personal_streamlit/pages/your_papers_page.py
personal_streamlit/read_backlog/notebooks/inspect_backlog.ipynb
personal_streamlit/read_backlog/read_backlog_table.py
personal_streamlit/start.py
personal_streamlit/utils/admin_utils.py
personal_streamlit/utils/ai_gen_utils.py
personal_streamlit/utils/help_utils.py
personal_streamlit/utils/login_utils.py
personal_streamlit/utils/paginator.py
personal_streamlit/utils/paper_details_utils.py
personal_streamlit/utils/papers_page_utils.py
personal_streamlit/utils/papers_renderer.py
personal_streamlit/utils/recommendations_utils.py
personal_streamlit/utils/sidebar_utils.py
personal_streamlit/utils/ui_components.py
state_of_the_art/CHANGELOG.md
state_of_the_art/README.md
state_of_the_art/__init__.py
state_of_the_art/bookmark.py
state_of_the_art/ci_cd.py
state_of_the_art/config.py
state_of_the_art/container_startup.py
state_of_the_art/image_processing/Images_extractor.py
state_of_the_art-0.2.0.dist-info/LICENSE.md
state_of_the_art-0.2.0.dist-info/METADATA
state_of_the_art-0.2.0.dist-info/WHEEL
state_of_the_art-0.2.0.dist-info/entry_points.txt
state_of_the_art-0.2.0.dist-info/RECORD
