Metadata-Version: 2.1
Name: state-of-the-art
Version: 0.2.0
Summary: Monorepo with state of the art project
Author: Jean Carlo Machado
Author-email: jean.machado@getyourguide.com
Requires-Python: >=3.12,<3.14
Classifier: Programming Language :: Python :: 3
Classifier: Programming Language :: Python :: 3.12
Classifier: Programming Language :: Python :: 3.13
Requires-Dist: accelerate (==0.31.0)
Requires-Dist: arxiv (>=2.1.0,<3.0.0)
Requires-Dist: beautifulsoup4 (>=4.12.3,<5.0.0)
Requires-Dist: datadog (>=0.50.1,<0.51.0)
Requires-Dist: ddtrace (>=2.14.4,<3.0.0)
Requires-Dist: django (>=5.2.1,<6.0.0)
Requires-Dist: fire
Requires-Dist: fpdf (>=1.7.2,<2.0.0)
Requires-Dist: gunicorn (>=23.0.0,<24.0.0)
Requires-Dist: jupyter (>=1.0.0,<2.0.0)
Requires-Dist: langchain (>=0.1.14,<0.2.0)
Requires-Dist: langchain-community (>=0.0.31,<0.0.32)
Requires-Dist: langchain-core (>=0.1.42,<0.2.0)
Requires-Dist: matplotlib (>=3.8.4,<4.0.0)
Requires-Dist: mlflow-skinny (>=2.17.2,<3.0.0)
Requires-Dist: nltk (>=3.8.1,<4.0.0)
Requires-Dist: openai (>=1.77,<2.0)
Requires-Dist: psutil (>=6.1.0,<7.0.0)
Requires-Dist: psycopg2-binary (>=2.9.10,<3.0.0)
Requires-Dist: pyarrow (>=20.0,<21.0)
Requires-Dist: pypdf (>=4.1.0,<5.0.0)
Requires-Dist: pytest (>=8.3.3,<9.0.0)
Requires-Dist: python-dotenv (>=1.1.0,<2.0.0)
Requires-Dist: rank-bm25 (>=0.2.2,<0.3.0)
Requires-Dist: schedule (>=1.2.2,<2.0.0)
Requires-Dist: scipy (>=1.14.1,<2.0.0)
Requires-Dist: sentence-transformers (>=3.0.1,<4.0.0)
Requires-Dist: tabulate (>=0.9.0,<0.10.0)
Requires-Dist: tiny-data-warehouse (>=0.2.2)
Requires-Dist: torchvision (>=0.22.0,<0.23.0)
Requires-Dist: tqdm (>=4.66.2,<5.0.0)
Requires-Dist: urlextract (>=1.9.0,<2.0.0)
